[
  {
    "activityId": 13608,
    "id": 0,
    "name1": "language_10119718",
    "name2": "language_10119719",
    "name3": "language_10119720"
  },
  {
    "activityId": 13608,
    "id": 1,
    "name1": "language_10119718",
    "name2": "language_10119719",
    "name3": "language_10119720"
  },
  {
    "activityId": 13608,
    "id": 2,
    "name1": "language_10119718",
    "name2": "language_10119719",
    "name3": "language_10119720"
  },
  {
    "activityId": 13608,
    "id": 3,
    "name1": "language_10119718",
    "name2": "language_10119719",
    "name3": "language_10119720"
  },
  {
    "activityId": 13608,
    "id": 4,
    "name1": "language_10119718",
    "name2": "language_10119719",
    "name3": "language_10119720"
  },
  {
    "activityId": 13608,
    "id": 5,
    "name1": "language_10119718",
    "name2": "language_10119719",
    "name3": "language_10119720"
  },
  {
    "activityId": 13608,
    "id": 6,
    "name1": "language_10119718",
    "name2": "language_10119719",
    "name3": "language_10119720"
  },
  {
    "activityId": 13608,
    "id": 7,
    "name1": "language_10119718",
    "name2": "language_10119719",
    "name3": "language_10119720"
  },
  {
    "activityId": 13608,
    "id": 8,
    "name1": "language_10119718",
    "name2": "language_10119719",
    "name3": "language_10119720"
  },
  {
    "activityId": 13608,
    "id": 9,
    "name1": "language_10119718",
    "name2": "language_10119719",
    "name3": "language_10119720"
  },
  {
    "activityId": 13608,
    "id": 10,
    "name1": "language_10119718",
    "name2": "language_10119719",
    "name3": "language_10119720"
  }
]