[
  {
    "activityId": 11304,
    "id": 101,
    "width": 8,
    "height": 8,
    "audioAmbient": 3300041,
    "bgPath": "scenes/v1a3_m_s12_dfw_zmsl/prefab/m_s12_dfw_zmsl_a01_p",
    "offset": "-1012.6,-85.6",
    "tilebase": "1,0,0,0,0,0,0,0,1,1,1,1,1,1,1,0,0,0,0,1,0,1,0,0,0,1,1,1,1,1,0,0,0,0,1,1,0,1,1,1,0,0,1,1,1,1,0,1,0,0,0,0,0,0,0,1,0,0,0,0,0,0,0,0",
    "objects": "[{\"posX\":0,\"actId\":11304,\"posY\":0,\"direction\":8,\"id\":10001},{\"posX\":5,\"actId\":11304,\"id\":10003,\"posY\":1},{\"posX\":2,\"actId\":11304,\"id\":10004,\"posY\":3},{\"posX\":5,\"actId\":11304,\"id\":10005,\"posY\":4},{\"posX\":3,\"actId\":11304,\"id\":10006,\"posY\":2},{\"posX\":3,\"actId\":11304,\"id\":10007,\"posY\":4},{\"posX\":5,\"actId\":11304,\"id\":10008,\"posY\":5},{\"posX\":7,\"actId\":11304,\"id\":10009,\"posY\":6}]",
    "decorateObjects": "[{\"posX\":3.5,\"actId\":11304,\"posY\":7,\"id\":30001 }]"
  },
  {
    "activityId": 11304,
    "id": 102,
    "width": 8,
    "height": 8,
    "audioAmbient": 3300041,
    "bgPath": "scenes/v1a3_m_s12_dfw_zmsl/prefab/m_s12_dfw_zmsl_a01_p",
    "offset": "-1012.6,-85.6",
    "tilebase": "0,0,0,0,0,0,0,0,1,0,0,0,0,0,0,0,1,1,1,0,1,1,1,1,1,1,1,0,1,1,1,1,0,1,0,0,1,1,1,1,0,1,0,0,1,0,1,0,0,1,1,1,1,0,1,0,0,0,0,0,0,0,1,0",
    "objects": "[{\"posX\":0,\"actId\":11304,\"posY\":1,\"direction\":4,\"id\":10001},{\"posX\":1,\"actId\":11304,\"id\":10003,\"posY\":3},{\"posX\":4,\"actId\":11304,\"id\":10004,\"posY\":3},{\"posX\":5,\"actId\":11304,\"id\":10005,\"posY\":3},{\"posX\":6,\"actId\":11304,\"id\":10010,\"posY\":4},{\"posX\":1,\"actId\":11304,\"id\":10013,\"posY\":6},{\"posX\":6,\"actId\":11304,\"id\":10014,\"posY\":6},{\"posX\":6,\"actId\":11304,\"id\":10015,\"posY\":7},{\"posX\":2,\"actId\":11304,\"id\":10008,\"posY\":3},{\"posX\":7,\"actId\":11304,\"id\":10011,\"posY\":4},{\"posX\":5,\"actId\":11304,\"id\":10012,\"posY\":2}]",
    "decorateObjects": "[{\"posX\":3.5,\"actId\":11304,\"posY\":0,\"id\":30001 }]"
  },
  {
    "activityId": 11304,
    "id": 201,
    "width": 8,
    "height": 8,
    "audioAmbient": 3300043,
    "bgPath": "scenes/v1a3_m_s12_dfw_zmsl/prefab/m_s12_dfw_zmsl_a02_p",
    "offset": "-960.8,-20",
    "tilebase": "1,1,1,1,1,1,1,0,1,1,1,1,0,1,1,1,1,1,1,1,0,1,1,0,1,1,1,1,0,0,1,1,0,0,0,1,0,1,1,1,0,1,1,1,0,1,1,0,0,1,1,0,0,0,1,1,0,1,1,1,1,0,0,0",
    "objects": "[{\"posX\":3,\"actId\":11304,\"posY\":4,\"direction\":4,\"id\":10024},{\"posX\":6,\"actId\":11304,,\"posY\":3,\"direction\":2,\"id\":10025},{\"posX\":3,\"actId\":11304,\"id\":10016,\"posY\":3},{\"posX\":2,\"actId\":11304,\"id\":10026,\"posY\":6},{\"posX\":0,\"actId\":11304,\"id\":10018,\"posY\":2},{\"posX\":1,\"actId\":11304,\"id\":10019,\"posY\":2},{\"posX\":1,\"actId\":11304,\"id\":10020,\"posY\":1},{\"posX\":2,\"actId\":11304,\"id\":10021,\"posY\":1},{\"posX\":5,\"actId\":11304,\"id\":10022,\"posY\":1},{\"posX\":6,\"actId\":11304,\"id\":10023,\"posY\":1},{\"posX\":6,\"actId\":11304,\"id\":10100,\"posY\":4},{\"posX\":3,\"actId\":11304,\"id\":10027,\"posY\":1},{\"posX\":3,\"actId\":11304,\"id\":10101,\"posY\":2},{\"posX\":7,\"actId\":11304,\"id\":10029,\"posY\":6},{\"posX\":5,\"actId\":11304,\"posY\":4,\"direction\":2,\"id\":10102},{\"posX\":4,\"actId\":11304,\"posY\":7,\"direction\":4,\"id\":100001}]",
    "decorateObjects": ""
  },
  {
    "activityId": 11304,
    "id": 202,
    "width": 8,
    "height": 8,
    "audioAmbient": 3300043,
    "bgPath": "scenes/v1a3_m_s12_dfw_zmsl/prefab/m_s12_dfw_zmsl_a02_p",
    "offset": "-960.8,-20",
    "tilebase": "0,1,1,1,1,1,1,0,0,1,0,0,1,1,1,0,0,1,1,0,1,1,1,0,0,1,0,1,1,1,0,1,0,1,0,1,1,1,0,1,0,1,0,1,1,1,0,1,1,1,0,1,1,1,1,1,0,1,0,0,1,0,0,1",
    "objects": "[{\"posX\":4,\"actId\":11304,\"id\":10021,\"posY\":6},{\"posX\":7,\"actId\":11304,\"posY\":6,\"direction\":8,\"id\":10031},{\"posX\":1,\"actId\":11304,\"id\":10030,\"posY\":3},{\"posX\":5,\"actId\":11304,\"id\":10020,\"posY\":5},{\"posX\":3,\"actId\":11304,\"id\":10027,\"posY\":6},{\"posX\":2,\"actId\":11304,\"id\":10102,\"posY\":2},{\"posX\":7,\"actId\":11304,\"id\":10015,\"posY\":3},{\"posX\":4,\"actId\":11304,\"id\":10018,\"posY\":4},{\"posX\":3,\"actId\":11304,\"id\":10019,\"posY\":5},{\"posX\":5,\"actId\":11304,\"id\":10022,\"posY\":2},{\"posX\":5,\"actId\":11304,\"id\":10023,\"posY\":1},{\"posX\":4,\"actId\":11304,\"id\":10101,\"posY\":2},{\"posX\":3,\"actId\":11304,\"id\":10026,\"posY\":4},{\"posX\":0,\"actId\":11304,\"posY\":6,\"direction\":6,\"id\":100001},{\"posX\":5,\"actId\":11304,\"id\":0,\"posY\":6},{\"posX\":1,\"actId\":11304,\"id\":100017,\"posY\":3}]",
    "decorateObjects": ""
  },
  {
    "activityId": 11304,
    "id": 301,
    "width": 8,
    "height": 8,
    "audioAmbient": 3300041,
    "bgPath": "scenes/v1a3_m_s12_dfw_zmsl/prefab/m_s12_dfw_zmsl_a01_p",
    "offset": "-1012.6,-85.6",
    "tilebase": "0,1,1,1,0,0,0,0,1,1,1,1,1,1,1,0,0,1,1,1,0,1,1,1,0,1,1,1,0,1,1,1,0,0,0,0,0,1,1,1,0,0,0,0,0,1,1,1,0,0,0,0,0,1,1,1,0,0,0,0,0,0,1,0",
    "objects": "[{\"posX\":3,\"actId\":11304,\"id\":10055,\"posY\":1},{\"posX\":6,\"actId\":11304,\"id\":10036,\"posY\":6},{\"posX\":0,\"actId\":11304,\"posY\":1,\"direction\":6,\"id\":10001},{\"posX\":1,\"actId\":11304,\"posY\":0,\"direction\":6,\"id\":20001},{\"posX\":3,\"actId\":11304,\"id\":10012,\"posY\":0},{\"posX\":3,\"actId\":11304,\"id\":10011,\"posY\":2},{\"posX\":3,\"actId\":11304,\"id\":10006,\"posY\":3},{\"posX\":6,\"actId\":11304,\"id\":10029,\"posY\":7},{\"posX\":6,\"actId\":11304,\"id\":10053,\"posY\":2},{\"posX\":5,\"actId\":11304,\"id\":10037,\"posY\":1},{\"posX\":5,\"actId\":11304,\"id\":10033,\"posY\":3},{\"posX\":6,\"actId\":11304,\"id\":10032,\"posY\":3},{\"posX\":7,\"actId\":11304,\"id\":10004,\"posY\":4},{\"posX\":5,\"actId\":11304,\"id\":10007,\"posY\":6},{\"posX\":2,\"actId\":11304,\"id\":10003,\"posY\":2},{\"posX\":6,\"actId\":11304,\"id\":10005,\"posY\":5},{\"posX\":6,\"actId\":11304,\"id\":1036,\"posY\":6}]",
    "decorateObjects": ""
  },
  {
    "activityId": 11304,
    "id": 302,
    "width": 8,
    "height": 8,
    "audioAmbient": 3300041,
    "bgPath": "scenes/v1a3_m_s12_dfw_zmsl/prefab/m_s12_dfw_zmsl_a01_p",
    "offset": "-1012.6,-85.6",
    "tilebase": "0,1,1,1,0,1,1,1,1,0,1,1,0,1,1,1,1,0,0,1,0,1,1,1,1,1,1,1,0,1,1,1,0,1,0,1,1,0,1,1,1,1,1,0,1,0,1,1,1,0,1,1,1,0,1,1,1,1,1,1,1,1,1,0",
    "objects": "[{\"posX\":3,\"actId\":11304,\"id\":10003,\"posY\":6},{\"posX\":6,\"actId\":11304,\"id\":10004,\"posY\":5},{\"posX\":6,\"actId\":11304,\"id\":10005,\"posY\":2},{\"posX\":6,\"actId\":11304,\"id\":10006,\"posY\":0},{\"posX\":7,\"actId\":11304,\"id\":10032,\"posY\":2},{\"posX\":5,\"actId\":11304,\"id\":10033,\"posY\":1},{\"posX\":3,\"actId\":11304,\"id\":10038,\"posY\":2},{\"posX\":2,\"actId\":11304,\"id\":10034,\"posY\":3},{\"posX\":6,\"actId\":11304,\"id\":10008,\"posY\":3},{\"posX\":5,\"actId\":11304,\"id\":10011,\"posY\":2},{\"posX\":7,\"actId\":11304,\"id\":10015,\"posY\":0},{\"posX\":3,\"actId\":11304,\"id\":10039,\"posY\":2},{\"posX\":1,\"actId\":11304,\"posY\":0,\"direction\":6,\"id\":10001},{\"posX\":3,\"actId\":11304,\"id\":100039,\"posY\":2}]",
    "decorateObjects": ""
  },
  {
    "activityId": 11304,
    "id": 401,
    "width": 8,
    "height": 8,
    "audioAmbient": 3300041,
    "bgPath": "scenes/v1a3_m_s12_dfw_zmsl/prefab/m_s12_dfw_zmsl_a01_p",
    "offset": "-1012.6,-85.6",
    "tilebase": "0,0,0,0,0,0,0,0,1,1,1,1,1,1,1,0,0,0,1,0,0,0,1,1,0,0,1,1,1,0,0,0,0,0,1,1,1,1,0,0,1,1,1,1,1,0,0,0,1,0,1,1,1,0,0,0,1,1,1,0,0,0,0,0",
    "objects": "[{\"posX\":0,\"actId\":11304,\"posY\":1,\"direction\":6,\"id\":10001},{\"posX\":3,\"actId\":11304,\"posY\":1,\"direction\":6,\"id\":10041},{\"posX\":2,\"actId\":11304,\"id\":10044,\"posY\":7},{\"posX\":2,\"actId\":11304,\"id\":100044,\"posY\":7},{\"posX\":3,\"actId\":11304,\"id\":10003,\"posY\":3},{\"posX\":4,\"actId\":11304,\"id\":10004,\"posY\":4},{\"posX\":2,\"actId\":11304,\"id\":10005,\"posY\":4},{\"posX\":4,\"actId\":11304,\"id\":10006,\"posY\":5},{\"posX\":2,\"actId\":11304,\"id\":10007,\"posY\":6},{\"posX\":1,\"actId\":11304,\"id\":10008,\"posY\":5},{\"posX\":3,\"actId\":11304,\"id\":10032,\"posY\":5},{\"posX\":4,\"actId\":11304,\"posY\":1,\"direction\":4,\"id\":10043},{\"posX\":7,\"actId\":11304,\"id\":10029,\"posY\":2}]",
    "decorateObjects": ""
  },
  {
    "activityId": 11304,
    "id": 402,
    "width": 8,
    "height": 8,
    "audioAmbient": 3300041,
    "bgPath": "scenes/v1a3_m_s12_dfw_zmsl/prefab/m_s12_dfw_zmsl_a01_p",
    "offset": "-1012.6,-85.6",
    "tilebase": "0,1,1,1,1,1,0,0,0,1,1,1,1,1,1,1,0,1,1,1,1,1,0,1,1,1,1,1,1,1,0,1,0,0,0,0,0,0,1,1,0,0,1,1,1,1,1,1,1,1,1,1,1,1,1,1,1,0,1,1,1,1,1,1",
    "objects": "[{\"posX\":0,\"actId\":11304,\"posY\":3,\"direction\":6,\"id\":10001},{\"posX\":1,\"actId\":11304,\"posY\":2,\"direction\":2,\"id\":10045},{\"posX\":2,\"actId\":11304,\"posY\":1,\"direction\":4,\"id\":10046},{\"posX\":3,\"actId\":11304,\"posY\":2,\"direction\":4,\"id\":10047},{\"posX\":5,\"actId\":11304,\"id\":10049,\"posY\":3},{\"posX\":7,\"actId\":11304,\"id\":10052,\"posY\":2},{\"posX\":0,\"actId\":11304,\"id\":10015,\"posY\":7},{\"posX\":5,\"actId\":11304,\"id\":20002,\"posY\":0},{\"posX\":6,\"actId\":11304,\"id\":10003,\"posY\":5},{\"posX\":5,\"actId\":11304,\"id\":10004,\"posY\":6},{\"posX\":3,\"actId\":11304,\"id\":10005,\"posY\":6},{\"posX\":4,\"actId\":11304,\"id\":10032,\"posY\":6},{\"posX\":3,\"actId\":11304,\"id\":10033,\"posY\":7},{\"posX\":7,\"actId\":11304,\"id\":10006,\"posY\":7},{\"posX\":2,\"actId\":11304,\"id\":10008,\"posY\":7},{\"posX\":4,\"actId\":11304,\"id\":10011,\"posY\":5},{\"posX\":0,\"actId\":11304,\"id\":10051,\"posY\":6},{\"posX\":1,\"actId\":11304,\"posY\":6,\"direction\":4,\"id\":10089},{\"posX\":4,\"actId\":11304,\"id\":10050,\"posY\":7},{\"posX\":1,\"actId\":11304,\"id\":100050,\"posY\":6}]",
    "decorateObjects": ""
  },
  {
    "activityId": 11304,
    "id": 501,
    "width": 8,
    "height": 8,
    "audioAmbient": 3300041,
    "bgPath": "scenes/v1a3_m_s12_dfw_zmsl/prefab/m_s12_dfw_zmsl_a01_p",
    "offset": "-1012.6,-85.6",
    "tilebase": "0,0,1,0,0,0,0,0,1,1,1,1,1,1,1,1,1,1,1,1,1,1,1,1,1,1,1,1,1,1,1,1,1,1,1,1,1,1,1,1,1,1,1,1,1,1,1,1,0,0,0,0,0,0,1,0,0,0,0,0,0,0,0,0",
    "objects": "[{\"posX\":2,\"actId\":11304,\"posY\":0,\"direction\":8,\"id\":10001},{\"posX\":1,\"actId\":11304,\"id\":10003,\"posY\":1},{\"posX\":3,\"actId\":11304,\"id\":10004,\"posY\":1},{\"posX\":2,\"actId\":11304,\"id\":10005,\"posY\":2},{\"posX\":0,\"actId\":11304,\"id\":10006,\"posY\":5},{\"posX\":4,\"actId\":11304,\"id\":10007,\"posY\":3},{\"posX\":4,\"actId\":11304,\"id\":10008,\"posY\":1},{\"posX\":2,\"actId\":11304,\"id\":10011,\"posY\":5},{\"posX\":5,\"actId\":11304,\"id\":10012,\"posY\":4},{\"posX\":1,\"actId\":11304,\"id\":10032,\"posY\":4},{\"posX\":0,\"actId\":11304,\"id\":10033,\"posY\":3},{\"posX\":7,\"actId\":11304,\"id\":10034,\"posY\":5},{\"posX\":1,\"actId\":11304,\"id\":10035,\"posY\":3},{\"posX\":2,\"actId\":11304,\"id\":10053,\"posY\":3},{\"posX\":3,\"actId\":11304,\"id\":10054,\"posY\":3},{\"posX\":4,\"actId\":11304,\"id\":10055,\"posY\":4},{\"posX\":3,\"actId\":11304,\"id\":10056,\"posY\":5},{\"posX\":5,\"actId\":11304,\"id\":10057,\"posY\":2},{\"posX\":6,\"actId\":11304,\"id\":10058,\"posY\":4},{\"posX\":6,\"actId\":11304,\"posY\":3,\"direction\":6,\"id\":10059},{\"posX\":6,\"actId\":11304,\"id\":10062,\"posY\":6}]",
    "decorateObjects": "[{\"posX\":3.5,\"actId\":11304,\"posY\":7,\"id\":30001 }]"
  },
  {
    "activityId": 11304,
    "id": 502,
    "width": 8,
    "height": 8,
    "audioAmbient": 3300041,
    "bgPath": "scenes/v1a3_m_s12_dfw_zmsl/prefab/m_s12_dfw_zmsl_a01_p",
    "offset": "-1012.6,-85.6",
    "tilebase": "0,0,0,0,0,0,0,0,1,1,1,1,1,1,1,0,1,1,1,1,1,1,1,0,1,1,1,1,1,1,1,0,1,1,1,0,0,0,0,0,0,1,0,1,1,1,0,0,0,1,0,1,1,1,1,1,0,1,1,1,1,1,0,0",
    "objects": "[{\"posX\":6,\"actId\":11304,\"posY\":1,\"direction\":4,\"id\":10001},{\"posX\":5,\"actId\":11304,\"id\":10003,\"posY\":2},{\"posX\":4,\"actId\":11304,\"id\":10004,\"posY\":1},{\"posX\":4,\"actId\":11304,\"id\":10005,\"posY\":3},{\"posX\":3,\"actId\":11304,\"id\":10006,\"posY\":3},{\"posX\":5,\"actId\":11304,\"id\":10008,\"posY\":3},{\"posX\":7,\"actId\":11304,\"id\":10015,\"posY\":6},{\"posX\":4,\"actId\":11304,\"id\":10057,\"posY\":6},{\"posX\":3,\"actId\":11304,\"posY\":7,\"direction\":6,\"id\":10060},{\"posX\":5,\"actId\":11304,\"posY\":5,\"direction\":4,\"id\":10061},{\"posX\":1,\"actId\":11304,\"id\":10063,\"posY\":6},{\"posX\":1,\"actId\":11304,\"id\":100063,\"posY\":6},{\"posX\":6,\"actId\":11304,\"id\":10064,\"posY\":6},{\"posX\":6,\"actId\":11304,\"id\":100064,\"posY\":6},{\"posX\":1,\"actId\":11304,\"id\":10053,\"posY\":2},{\"posX\":3,\"actId\":11304,\"id\":10011,\"posY\":1},{\"posX\":2,\"actId\":11304,\"id\":20004,\"posY\":1},{\"posX\":2,\"actId\":11304,\"id\":20003,\"posY\":3},{\"posX\":6,\"actId\":11304,\"id\":100062,\"posY\":1}]",
    "decorateObjects": "[{\"posX\":3.5,\"actId\":11304,\"posY\":0,\"id\":30001 }]"
  },
  {
    "activityId": 11304,
    "id": 601,
    "width": 8,
    "height": 8,
    "audioAmbient": 3300041,
    "bgPath": "scenes/v1a3_m_s12_dfw_zmsl/prefab/m_s12_dfw_zmsl_a01_p",
    "offset": "-1012.6,-85.6",
    "tilebase": "1,1,1,1,0,1,1,1,1,1,1,1,0,1,0,1,1,1,1,1,0,1,1,1,1,1,1,1,0,0,1,1,1,0,0,1,1,1,1,1,1,1,1,1,0,1,1,1,0,0,0,1,0,1,1,1,0,0,0,1,0,0,0,0",
    "objects": "[{\"posX\":3,\"actId\":11304,\"id\":10001,\"posY\":7},{\"posX\":3,\"actId\":11304,\"id\":10065,\"posY\":5},{\"posX\":3,\"actId\":11304,\"id\":100065,\"posY\":5},{\"posX\":0,\"actId\":11304,\"posY\":2,\"direction\":6,\"id\":10066},{\"posX\":0,\"actId\":11304,\"id\":10068,\"posY\":0},{\"posX\":3,\"actId\":11304,\"id\":10067,\"posY\":2},{\"posX\":4,\"actId\":11304,\"id\":10071,\"posY\":4},{\"posX\":4,\"actId\":11304,\"id\":100071,\"posY\":4},{\"posX\":3,\"actId\":11304,\"id\":10003,\"posY\":4},{\"posX\":5,\"actId\":11304,\"id\":10004,\"posY\":5},{\"posX\":5,\"actId\":11304,\"id\":10005,\"posY\":4},{\"posX\":7,\"actId\":11304,\"id\":10032,\"posY\":5},{\"posX\":1,\"actId\":11304,\"id\":10006,\"posY\":3},{\"posX\":6,\"actId\":11304,\"id\":10007,\"posY\":3},{\"posX\":3,\"actId\":11304,\"id\":10011,\"posY\":3},{\"posX\":6,\"actId\":11304,\"id\":10012,\"posY\":2},{\"posX\":7,\"actId\":11304,\"id\":10029,\"posY\":0}]",
    "decorateObjects": ""
  },
  {
    "activityId": 11304,
    "id": 602,
    "width": 8,
    "height": 8,
    "audioAmbient": 3300041,
    "bgPath": "scenes/v1a3_m_s12_dfw_zmsl/prefab/m_s12_dfw_zmsl_a01_p",
    "offset": "-1012.6,-85.6",
    "tilebase": "1,1,1,0,1,1,1,1,1,1,1,0,1,1,1,0,1,1,1,1,1,1,1,1,1,1,1,0,1,1,1,1,1,1,1,0,1,1,1,1,1,1,1,1,1,1,1,1,1,1,1,0,1,1,1,1,0,0,0,0,0,0,0,1",
    "objects": "[{\"posX\":0,\"actId\":11304,\"posY\":0,\"direction\":6,\"id\":10001},{\"posX\":7,\"actId\":11304,\"posY\":0,\"direction\":4,\"id\":10002},{\"posX\":0,\"actId\":11304,\"id\":10003,\"posY\":5},{\"posX\":1,\"actId\":11304,\"id\":10004,\"posY\":4},{\"posX\":2,\"actId\":11304,\"id\":10005,\"posY\":3},{\"posX\":4,\"actId\":11304,\"id\":10006,\"posY\":3},{\"posX\":5,\"actId\":11304,\"id\":10007,\"posY\":3},{\"posX\":6,\"actId\":11304,\"id\":10008,\"posY\":5},{\"posX\":7,\"actId\":11304,\"posY\":7,\"direction\":2,\"id\":10015},{\"posX\":5,\"actId\":11304,\"posY\":2,\"direction\":6,\"id\":10069},{\"posX\":6,\"actId\":11304,\"posY\":2,\"direction\":6,\"id\":10070},{\"posX\":0,\"actId\":11304,\"id\":10072,\"posY\":6},{\"posX\":7,\"actId\":11304,\"posY\":6,\"direction\":6,\"id\":10073},{\"posX\":5,\"actId\":11304,\"id\":10057,\"posY\":4},{\"posX\":4,\"actId\":11304,\"id\":10058,\"posY\":6},{\"posX\":2,\"actId\":11304,\"id\":10032,\"posY\":2},{\"posX\":5,\"actId\":11304,\"id\":10033,\"posY\":5},{\"posX\":2,\"actId\":11304,\"id\":10034,\"posY\":4},{\"posX\":1,\"actId\":11304,\"id\":10035,\"posY\":5}]",
    "decorateObjects": ""
  },
  {
    "activityId": 11304,
    "id": 701,
    "width": 8,
    "height": 8,
    "audioAmbient": 3300041,
    "bgPath": "scenes/v1a3_m_s12_dfw_zmsl/prefab/m_s12_dfw_zmsl_a01_p",
    "offset": "-1012.6,-85.6",
    "tilebase": "1,1,1,1,1,1,1,1,1,0,1,1,1,1,1,1,1,0,1,1,1,1,1,1,0,0,0,1,1,1,1,1,0,0,0,1,1,1,0,1,1,0,1,1,1,1,1,0,1,0,1,1,1,1,1,0,1,1,1,1,1,1,1,0",
    "objects": "[{\"posX\":0,\"actId\":11304,\"id\":10001,\"posY\":2},{\"posX\":0,\"actId\":11304,\"posY\":5,\"direction\":8,\"id\":10002},{\"posX\":3,\"actId\":11304,\"id\":10003,\"posY\":3},{\"posX\":4,\"actId\":11304,\"id\":10004,\"posY\":4},{\"posX\":4,\"actId\":11304,\"id\":10005,\"posY\":5},{\"posX\":5,\"actId\":11304,\"id\":10032,\"posY\":6},{\"posX\":4,\"actId\":11304,\"id\":10033,\"posY\":7},{\"posX\":5,\"actId\":11304,\"id\":10006,\"posY\":2},{\"posX\":5,\"actId\":11304,\"id\":10007,\"posY\":1},{\"posX\":3,\"actId\":11304,\"id\":10008,\"posY\":4},{\"posX\":4,\"actId\":11304,\"id\":10053,\"posY\":2},{\"posX\":4,\"actId\":11304,\"id\":10054,\"posY\":1},{\"posX\":4,\"actId\":11304,\"id\":10055,\"posY\":0},{\"posX\":6,\"actId\":11304,\"id\":10056,\"posY\":2},{\"posX\":5,\"actId\":11304,\"id\":10057,\"posY\":0},{\"posX\":6,\"actId\":11304,\"id\":10058,\"posY\":0},{\"posX\":7,\"actId\":11304,\"id\":10074,\"posY\":2},{\"posX\":7,\"actId\":11304,\"id\":10034,\"posY\":1},{\"posX\":7,\"actId\":11304,\"id\":10035,\"posY\":0},{\"posX\":2,\"actId\":11304,\"posY\":0,\"direction\":8,\"id\":10076},{\"posX\":2,\"actId\":11304,\"id\":10077,\"posY\":7},{\"posX\":4,\"actId\":11304,\"id\":10079,\"posY\":3},{\"posX\":6,\"actId\":11304,\"id\":10080,\"posY\":1},{\"posX\":7,\"actId\":11304,\"id\":10029,\"posY\":4}]",
    "decorateObjects": ""
  },
  {
    "activityId": 11304,
    "id": 702,
    "width": 8,
    "height": 8,
    "audioAmbient": 3300041,
    "bgPath": "scenes/v1a3_m_s12_dfw_zmsl/prefab/m_s12_dfw_zmsl_a01_p",
    "offset": "-1012.6,-85.6",
    "tilebase": "0,0,0,0,0,0,1,0,1,1,1,0,0,0,1,0,1,1,1,0,1,0,1,0,1,0,1,1,1,1,1,1,1,0,1,0,1,1,1,1,1,1,1,1,1,1,1,1,1,1,1,1,1,1,1,0,0,0,1,1,1,1,1,0",
    "objects": "[{\"posX\":0,\"actId\":11304,\"id\":10001,\"posY\":3},{\"posX\":0,\"actId\":11304,\"posY\":4,\"direction\":8,\"id\":10002},{\"posX\":0,\"actId\":11304,\"id\":10003,\"posY\":2},{\"posX\":3,\"actId\":11304,\"id\":10004,\"posY\":7},{\"posX\":3,\"actId\":11304,\"id\":10005,\"posY\":5},{\"posX\":0,\"actId\":11304,\"id\":10006,\"posY\":6},{\"posX\":1,\"actId\":11304,\"id\":10007,\"posY\":5},{\"posX\":0,\"actId\":11304,\"id\":10008,\"posY\":1},{\"posX\":4,\"actId\":11304,\"id\":10032,\"posY\":6},{\"posX\":4,\"actId\":11304,\"id\":10033,\"posY\":5},{\"posX\":4,\"actId\":11304,\"id\":10034,\"posY\":7},{\"posX\":6,\"actId\":11304,\"id\":10058,\"posY\":5},{\"posX\":5,\"actId\":11304,\"id\":10057,\"posY\":4},{\"posX\":3,\"actId\":11304,\"id\":10075,\"posY\":3},{\"posX\":5,\"actId\":11304,\"id\":10074,\"posY\":6},{\"posX\":1,\"actId\":11304,\"posY\":2,\"direction\":6,\"id\":10078},{\"posX\":7,\"actId\":11304,\"id\":10081,\"posY\":5},{\"posX\":6,\"actId\":11304,\"id\":10015,\"posY\":0},{\"posX\":6,\"actId\":11304,\"id\":1081,\"posY\":0},{\"posX\":6,\"actId\":11304,\"id\":1082,\"posY\":0}]",
    "decorateObjects": ""
  },
  {
    "activityId": 11304,
    "id": 801,
    "width": 8,
    "height": 8,
    "audioAmbient": 3300043,
    "bgPath": "scenes/v1a3_m_s12_dfw_zmsl/prefab/m_s12_dfw_zmsl_a02_p",
    "offset": "-960.8,-20",
    "tilebase": "0,0,0,0,0,0,0,0,1,1,1,1,0,0,0,0,1,1,1,1,1,1,0,0,1,1,1,0,1,1,1,1,1,1,1,1,1,0,0,0,0,0,0,0,1,0,0,0,1,1,1,1,1,0,0,0,0,0,0,0,0,0,0,0",
    "objects": "[{\"posX\":7,\"actId\":11304,\"id\":10029,\"posY\":3},{\"posX\":5,\"actId\":11304,\"posY\":3,\"direction\":2,\"id\":10086},{\"posX\":4,\"actId\":11304,\"posY\":5,\"direction\":4,\"id\":10087},{\"posX\":0,\"actId\":11304,\"id\":10026,\"posY\":4},{\"posX\":0,\"actId\":11304,\"posY\":6,\"direction\":6,\"id\":100001},{\"posX\":2,\"actId\":11304,\"id\":10027,\"posY\":3},{\"posX\":2,\"actId\":11304,\"id\":10102,\"posY\":1},{\"posX\":1,\"actId\":11304,\"id\":10021,\"posY\":2},{\"posX\":1,\"actId\":11304,\"id\":10022,\"posY\":1},{\"posX\":4,\"actId\":11304,\"id\":10019,\"posY\":3},{\"posX\":4,\"actId\":11304,\"id\":10020,\"posY\":2},{\"posX\":3,\"actId\":11304,\"id\":10083,\"posY\":4},{\"posX\":3,\"actId\":11304,\"id\":100083,\"posY\":4},{\"posX\":2,\"actId\":11304,\"id\":0,\"posY\":4}]",
    "decorateObjects": ""
  },
  {
    "activityId": 11304,
    "id": 802,
    "width": 8,
    "height": 8,
    "audioAmbient": 3300043,
    "bgPath": "scenes/v1a3_m_s12_dfw_zmsl/prefab/m_s12_dfw_zmsl_a02_p",
    "offset": "-960.8,-20",
    "tilebase": "0,0,0,0,0,0,0,0,0,0,0,1,1,1,1,0,0,1,1,1,1,1,1,1,1,1,0,1,1,1,1,1,0,0,0,1,1,1,1,1,0,0,0,0,0,0,1,1,1,1,1,1,1,1,1,0,0,0,0,0,0,0,0,0",
    "objects": "[{\"posX\":0,\"actId\":11304,\"posY\":3,\"direction\":6,\"id\":100001},{\"posX\":2,\"actId\":11304,\"id\":10085,\"posY\":2},{\"posX\":2,\"actId\":11304,\"id\":100085,\"posY\":2},{\"posX\":3,\"actId\":11304,\"id\":10018,\"posY\":3},{\"posX\":4,\"actId\":11304,\"id\":10019,\"posY\":4},{\"posX\":4,\"actId\":11304,\"id\":10020,\"posY\":2},{\"posX\":5,\"actId\":11304,\"id\":10021,\"posY\":1},{\"posX\":5,\"actId\":11304,\"id\":10022,\"posY\":2},{\"posX\":5,\"actId\":11304,\"id\":10023,\"posY\":3},{\"posX\":6,\"actId\":11304,\"id\":10100,\"posY\":3},{\"posX\":0,\"actId\":11304,\"id\":10015,\"posY\":6},{\"posX\":3,\"actId\":11304,\"id\":10026,\"posY\":4},{\"posX\":6,\"actId\":11304,\"id\":10027,\"posY\":2},{\"posX\":5,\"actId\":11304,\"posY\":6,\"direction\":6,\"id\":10088}]",
    "decorateObjects": ""
  }
]