[
  {
    "id": 10001001,
    "unlockCondition": "",
    "notFinish": 0,
    "desc": "language_10130592",
    "subDesc": "",
    "reward": "",
    "warning": 0,
    "dataBase": 0,
    "story": 0,
    "puzzle": ""
  },
  {
    "id": 10001002,
    "unlockCondition": "",
    "notFinish": 0,
    "desc": "language_10130593",
    "subDesc": "",
    "reward": "",
    "warning": 0,
    "dataBase": 0,
    "story": 0,
    "puzzle": ""
  },
  {
    "id": 10001003,
    "unlockCondition": "",
    "notFinish": 0,
    "desc": "language_10130594",
    "subDesc": "",
    "reward": "",
    "warning": 0,
    "dataBase": 0,
    "story": 0,
    "puzzle": ""
  },
  {
    "id": 10002001,
    "unlockCondition": "",
    "notFinish": 0,
    "desc": "language_10130595",
    "subDesc": "",
    "reward": "2#38501#8",
    "warning": 0,
    "dataBase": 0,
    "story": 0,
    "puzzle": ""
  },
  {
    "id": 10002002,
    "unlockCondition": "",
    "notFinish": 0,
    "desc": "language_10130596",
    "subDesc": "",
    "reward": "2#38501#8",
    "warning": 0,
    "dataBase": 0,
    "story": 0,
    "puzzle": ""
  },
  {
    "id": 10002003,
    "unlockCondition": "",
    "notFinish": 0,
    "desc": "language_10029754",
    "subDesc": "",
    "reward": "",
    "warning": 0,
    "dataBase": 0,
    "story": 0,
    "puzzle": ""
  },
  {
    "id": 10004001,
    "unlockCondition": "",
    "notFinish": 0,
    "desc": "language_10130597",
    "subDesc": "",
    "reward": "",
    "warning": 20,
    "dataBase": 0,
    "story": 0,
    "puzzle": ""
  },
  {
    "id": 10004002,
    "unlockCondition": "",
    "notFinish": 0,
    "desc": "language_10130598",
    "subDesc": "",
    "reward": "2#38501#5",
    "warning": 0,
    "dataBase": 0,
    "story": 0,
    "puzzle": ""
  },
  {
    "id": 10004003,
    "unlockCondition": "",
    "notFinish": 0,
    "desc": "language_10000985",
    "subDesc": "",
    "reward": "",
    "warning": 0,
    "dataBase": 0,
    "story": 0,
    "puzzle": ""
  },
  {
    "id": 10005001,
    "unlockCondition": "",
    "notFinish": 0,
    "desc": "language_10130599",
    "subDesc": "",
    "reward": "",
    "warning": 0,
    "dataBase": 0,
    "story": 0,
    "puzzle": ""
  },
  {
    "id": 10005002,
    "unlockCondition": "",
    "notFinish": 0,
    "desc": "language_10130600",
    "subDesc": "",
    "reward": "",
    "warning": 0,
    "dataBase": 0,
    "story": 0,
    "puzzle": ""
  },
  {
    "id": 10005003,
    "unlockCondition": "",
    "notFinish": 0,
    "desc": "language_10130601",
    "subDesc": "",
    "reward": "",
    "warning": 0,
    "dataBase": 0,
    "story": 0,
    "puzzle": ""
  },
  {
    "id": 10009001,
    "unlockCondition": "",
    "notFinish": 0,
    "desc": "language_10130602",
    "subDesc": "",
    "reward": "",
    "warning": 0,
    "dataBase": 0,
    "story": 0,
    "puzzle": ""
  },
  {
    "id": 10009002,
    "unlockCondition": "",
    "notFinish": 0,
    "desc": "language_10130603",
    "subDesc": "",
    "reward": "",
    "warning": 0,
    "dataBase": 0,
    "story": 0,
    "puzzle": ""
  },
  {
    "id": 10009003,
    "unlockCondition": "",
    "notFinish": 0,
    "desc": "language_90016068",
    "subDesc": "",
    "reward": "",
    "warning": 0,
    "dataBase": 0,
    "story": 0,
    "puzzle": ""
  },
  {
    "id": 10010001,
    "unlockCondition": "",
    "notFinish": 0,
    "desc": "language_10130604",
    "subDesc": "",
    "reward": "",
    "warning": -25,
    "dataBase": 0,
    "story": 0,
    "puzzle": ""
  },
  {
    "id": 10010002,
    "unlockCondition": "",
    "notFinish": 0,
    "desc": "language_10130605",
    "subDesc": "",
    "reward": "2#38501#8",
    "warning": 0,
    "dataBase": 0,
    "story": 0,
    "puzzle": ""
  },
  {
    "id": 10010003,
    "unlockCondition": "",
    "notFinish": 0,
    "desc": "language_10001221",
    "subDesc": "",
    "reward": "",
    "warning": 0,
    "dataBase": 0,
    "story": 0,
    "puzzle": ""
  },
  {
    "id": 10019001,
    "unlockCondition": "",
    "notFinish": 0,
    "desc": "language_10130606",
    "subDesc": "",
    "reward": "",
    "warning": 0,
    "dataBase": 0,
    "story": 0,
    "puzzle": ""
  },
  {
    "id": 20001001,
    "unlockCondition": "",
    "notFinish": 0,
    "desc": "language_10130607",
    "subDesc": "",
    "reward": "",
    "warning": 0,
    "dataBase": 0,
    "story": 0,
    "puzzle": ""
  },
  {
    "id": 20002001,
    "unlockCondition": "",
    "notFinish": 0,
    "desc": "language_10130608",
    "subDesc": "",
    "reward": "",
    "warning": 0,
    "dataBase": 0,
    "story": 0,
    "puzzle": ""
  },
  {
    "id": 20002002,
    "unlockCondition": "",
    "notFinish": 0,
    "desc": "language_10130609",
    "subDesc": "",
    "reward": "",
    "warning": 0,
    "dataBase": 0,
    "story": 0,
    "puzzle": ""
  },
  {
    "id": 20002003,
    "unlockCondition": "",
    "notFinish": 0,
    "desc": "language_10130610",
    "subDesc": "",
    "reward": "",
    "warning": 0,
    "dataBase": 0,
    "story": 0,
    "puzzle": ""
  },
  {
    "id": 20003001,
    "unlockCondition": "",
    "notFinish": 0,
    "desc": "language_10130611",
    "subDesc": "",
    "reward": "2#38501#5",
    "warning": 0,
    "dataBase": 0,
    "story": 0,
    "puzzle": ""
  },
  {
    "id": 20003002,
    "unlockCondition": "",
    "notFinish": 0,
    "desc": "language_10130612",
    "subDesc": "",
    "reward": "",
    "warning": 20,
    "dataBase": 0,
    "story": 0,
    "puzzle": ""
  },
  {
    "id": 20003003,
    "unlockCondition": "",
    "notFinish": 0,
    "desc": "language_10130610",
    "subDesc": "",
    "reward": "",
    "warning": 0,
    "dataBase": 0,
    "story": 0,
    "puzzle": ""
  },
  {
    "id": 20012001,
    "unlockCondition": "",
    "notFinish": 0,
    "desc": "language_10130613",
    "subDesc": "",
    "reward": "",
    "warning": 0,
    "dataBase": 0,
    "story": 0,
    "puzzle": ""
  },
  {
    "id": 20012002,
    "unlockCondition": "",
    "notFinish": 0,
    "desc": "language_10130614",
    "subDesc": "",
    "reward": "",
    "warning": 0,
    "dataBase": 0,
    "story": 0,
    "puzzle": ""
  },
  {
    "id": 20012003,
    "unlockCondition": "",
    "notFinish": 0,
    "desc": "language_10130615",
    "subDesc": "",
    "reward": "",
    "warning": 0,
    "dataBase": 0,
    "story": 0,
    "puzzle": ""
  },
  {
    "id": 20012004,
    "unlockCondition": "",
    "notFinish": 0,
    "desc": "language_10130616",
    "subDesc": "",
    "reward": "",
    "warning": 0,
    "dataBase": 0,
    "story": 0,
    "puzzle": ""
  },
  {
    "id": 20012005,
    "unlockCondition": "",
    "notFinish": 0,
    "desc": "language_10130617",
    "subDesc": "",
    "reward": "",
    "warning": 0,
    "dataBase": 0,
    "story": 0,
    "puzzle": ""
  },
  {
    "id": 20013001,
    "unlockCondition": "",
    "notFinish": 0,
    "desc": "language_10130618",
    "subDesc": "",
    "reward": "",
    "warning": 25,
    "dataBase": 0,
    "story": 0,
    "puzzle": ""
  },
  {
    "id": 20013002,
    "unlockCondition": "",
    "notFinish": 0,
    "desc": "language_10130619",
    "subDesc": "",
    "reward": "",
    "warning": 25,
    "dataBase": 0,
    "story": 0,
    "puzzle": ""
  },
  {
    "id": 20013003,
    "unlockCondition": "",
    "notFinish": 0,
    "desc": "language_10130620",
    "subDesc": "",
    "reward": "",
    "warning": 0,
    "dataBase": 0,
    "story": 0,
    "puzzle": ""
  },
  {
    "id": 20017001,
    "unlockCondition": "",
    "notFinish": 0,
    "desc": "language_10034299",
    "subDesc": "",
    "reward": "",
    "warning": 0,
    "dataBase": 0,
    "story": 0,
    "puzzle": ""
  },
  {
    "id": 20017002,
    "unlockCondition": "",
    "notFinish": 0,
    "desc": "language_10130621",
    "subDesc": "",
    "reward": "",
    "warning": 0,
    "dataBase": 0,
    "story": 0,
    "puzzle": ""
  },
  {
    "id": 20018001,
    "unlockCondition": "",
    "notFinish": 0,
    "desc": "language_10130606",
    "subDesc": "",
    "reward": "",
    "warning": 0,
    "dataBase": 0,
    "story": 0,
    "puzzle": ""
  },
  {
    "id": 30001001,
    "unlockCondition": "",
    "notFinish": 0,
    "desc": "language_10130622",
    "subDesc": "",
    "reward": "2#38501#4",
    "warning": 0,
    "dataBase": 0,
    "story": 0,
    "puzzle": ""
  },
  {
    "id": 30001002,
    "unlockCondition": "",
    "notFinish": 0,
    "desc": "language_10130623",
    "subDesc": "",
    "reward": "2#38501#4",
    "warning": 0,
    "dataBase": 0,
    "story": 0,
    "puzzle": ""
  },
  {
    "id": 30001003,
    "unlockCondition": "",
    "notFinish": 0,
    "desc": "language_10130624",
    "subDesc": "",
    "reward": "",
    "warning": 0,
    "dataBase": 0,
    "story": 0,
    "puzzle": ""
  },
  {
    "id": 30002001,
    "unlockCondition": "",
    "notFinish": 0,
    "desc": "language_10029298",
    "subDesc": "",
    "reward": "",
    "warning": 0,
    "dataBase": 0,
    "story": 0,
    "puzzle": ""
  },
  {
    "id": 30004001,
    "unlockCondition": "",
    "notFinish": 0,
    "desc": "language_10122405",
    "subDesc": "",
    "reward": "",
    "warning": 0,
    "dataBase": 0,
    "story": 0,
    "puzzle": ""
  },
  {
    "id": 30005001,
    "unlockCondition": "",
    "notFinish": 0,
    "desc": "language_10130625",
    "subDesc": "",
    "reward": "",
    "warning": 0,
    "dataBase": 0,
    "story": 0,
    "puzzle": ""
  },
  {
    "id": 30009001,
    "unlockCondition": "",
    "notFinish": 0,
    "desc": "language_10130626",
    "subDesc": "",
    "reward": "",
    "warning": 0,
    "dataBase": 0,
    "story": 0,
    "puzzle": ""
  },
  {
    "id": 30009002,
    "unlockCondition": "",
    "notFinish": 0,
    "desc": "language_10130627",
    "subDesc": "",
    "reward": "",
    "warning": 0,
    "dataBase": 0,
    "story": 0,
    "puzzle": ""
  },
  {
    "id": 30009003,
    "unlockCondition": "",
    "notFinish": 0,
    "desc": "language_10130628",
    "subDesc": "",
    "reward": "",
    "warning": 0,
    "dataBase": 0,
    "story": 0,
    "puzzle": ""
  },
  {
    "id": 30019001,
    "unlockCondition": "",
    "notFinish": 0,
    "desc": "language_10130629",
    "subDesc": "",
    "reward": "",
    "warning": -30,
    "dataBase": 0,
    "story": 0,
    "puzzle": ""
  },
  {
    "id": 30019002,
    "unlockCondition": "",
    "notFinish": 0,
    "desc": "language_10130630",
    "subDesc": "",
    "reward": "",
    "warning": 25,
    "dataBase": 0,
    "story": 0,
    "puzzle": ""
  },
  {
    "id": 30019003,
    "unlockCondition": "",
    "notFinish": 0,
    "desc": "language_10130503",
    "subDesc": "",
    "reward": "",
    "warning": 0,
    "dataBase": 0,
    "story": 0,
    "puzzle": ""
  },
  {
    "id": 30020001,
    "unlockCondition": "",
    "notFinish": 0,
    "desc": "language_10130631",
    "subDesc": "",
    "reward": "",
    "warning": 0,
    "dataBase": 0,
    "story": 0,
    "puzzle": ""
  },
  {
    "id": 30020002,
    "unlockCondition": "",
    "notFinish": 0,
    "desc": "language_10130632",
    "subDesc": "",
    "reward": "",
    "warning": 0,
    "dataBase": 0,
    "story": 0,
    "puzzle": ""
  },
  {
    "id": 30021001,
    "unlockCondition": "",
    "notFinish": 0,
    "desc": "language_10130606",
    "subDesc": "",
    "reward": "",
    "warning": 0,
    "dataBase": 0,
    "story": 0,
    "puzzle": ""
  },
  {
    "id": 40001001,
    "unlockCondition": "",
    "notFinish": 0,
    "desc": "language_10130633",
    "subDesc": "",
    "reward": "",
    "warning": 0,
    "dataBase": 0,
    "story": 0,
    "puzzle": ""
  },
  {
    "id": 40002001,
    "unlockCondition": "",
    "notFinish": 0,
    "desc": "language_10130634",
    "subDesc": "",
    "reward": "2#38501#5",
    "warning": 0,
    "dataBase": 0,
    "story": 0,
    "puzzle": ""
  },
  {
    "id": 40002002,
    "unlockCondition": "",
    "notFinish": 0,
    "desc": "language_10130635",
    "subDesc": "",
    "reward": "2#38501#5",
    "warning": 0,
    "dataBase": 0,
    "story": 0,
    "puzzle": ""
  },
  {
    "id": 40002003,
    "unlockCondition": "",
    "notFinish": 0,
    "desc": "language_10130636",
    "subDesc": "",
    "reward": "",
    "warning": 0,
    "dataBase": 0,
    "story": 0,
    "puzzle": ""
  },
  {
    "id": 40003001,
    "unlockCondition": "",
    "notFinish": 0,
    "desc": "language_10130637",
    "subDesc": "",
    "reward": "",
    "warning": 0,
    "dataBase": 0,
    "story": 0,
    "puzzle": ""
  },
  {
    "id": 40003002,
    "unlockCondition": "",
    "notFinish": 0,
    "desc": "language_10130617",
    "subDesc": "",
    "reward": "",
    "warning": 0,
    "dataBase": 0,
    "story": 0,
    "puzzle": ""
  },
  {
    "id": 40008001,
    "unlockCondition": "",
    "notFinish": 0,
    "desc": "language_10130638",
    "subDesc": "",
    "reward": "",
    "warning": -20,
    "dataBase": 0,
    "story": 0,
    "puzzle": ""
  },
  {
    "id": 40008002,
    "unlockCondition": "",
    "notFinish": 0,
    "desc": "language_10130639",
    "subDesc": "",
    "reward": "",
    "warning": 40,
    "dataBase": 0,
    "story": 0,
    "puzzle": ""
  },
  {
    "id": 40008003,
    "unlockCondition": "",
    "notFinish": 0,
    "desc": "language_10130640",
    "subDesc": "",
    "reward": "",
    "warning": 0,
    "dataBase": 0,
    "story": 0,
    "puzzle": ""
  },
  {
    "id": 40013001,
    "unlockCondition": "",
    "notFinish": 0,
    "desc": "language_10130641",
    "subDesc": "",
    "reward": "",
    "warning": 0,
    "dataBase": 0,
    "story": 0,
    "puzzle": ""
  },
  {
    "id": 40013002,
    "unlockCondition": "",
    "notFinish": 0,
    "desc": "language_10130642",
    "subDesc": "",
    "reward": "",
    "warning": 0,
    "dataBase": 0,
    "story": 0,
    "puzzle": ""
  },
  {
    "id": 40013003,
    "unlockCondition": "",
    "notFinish": 0,
    "desc": "language_10028496",
    "subDesc": "",
    "reward": "",
    "warning": 0,
    "dataBase": 0,
    "story": 0,
    "puzzle": ""
  },
  {
    "id": 40018001,
    "unlockCondition": "",
    "notFinish": 0,
    "desc": "language_10130643",
    "subDesc": "",
    "reward": "2#38501#10",
    "warning": 0,
    "dataBase": 0,
    "story": 0,
    "puzzle": ""
  },
  {
    "id": 40018002,
    "unlockCondition": "",
    "notFinish": 0,
    "desc": "language_10130644",
    "subDesc": "",
    "reward": "",
    "warning": -15,
    "dataBase": 0,
    "story": 0,
    "puzzle": ""
  },
  {
    "id": 40018003,
    "unlockCondition": "",
    "notFinish": 0,
    "desc": "language_10130645",
    "subDesc": "",
    "reward": "",
    "warning": 0,
    "dataBase": 0,
    "story": 0,
    "puzzle": ""
  },
  {
    "id": 40019001,
    "unlockCondition": "",
    "notFinish": 0,
    "desc": "language_10130606",
    "subDesc": "",
    "reward": "",
    "warning": 0,
    "dataBase": 0,
    "story": 0,
    "puzzle": ""
  },
  {
    "id": 50001001,
    "unlockCondition": "",
    "notFinish": 0,
    "desc": "language_10130646",
    "subDesc": "",
    "reward": "2#38501#5",
    "warning": 0,
    "dataBase": 0,
    "story": 0,
    "puzzle": ""
  },
  {
    "id": 50001002,
    "unlockCondition": "",
    "notFinish": 0,
    "desc": "language_10130647",
    "subDesc": "",
    "reward": "2#38501#5",
    "warning": 0,
    "dataBase": 0,
    "story": 0,
    "puzzle": ""
  },
  {
    "id": 50001003,
    "unlockCondition": "",
    "notFinish": 0,
    "desc": "language_10130648",
    "subDesc": "",
    "reward": "2#38501#5",
    "warning": 0,
    "dataBase": 0,
    "story": 0,
    "puzzle": ""
  },
  {
    "id": 50001004,
    "unlockCondition": "",
    "notFinish": 0,
    "desc": "language_90016072",
    "subDesc": "",
    "reward": "",
    "warning": 0,
    "dataBase": 0,
    "story": 0,
    "puzzle": ""
  },
  {
    "id": 50002001,
    "unlockCondition": "",
    "notFinish": 0,
    "desc": "language_10130649",
    "subDesc": "",
    "reward": "",
    "warning": 0,
    "dataBase": 0,
    "story": 0,
    "puzzle": ""
  },
  {
    "id": 50002002,
    "unlockCondition": "",
    "notFinish": 0,
    "desc": "language_10130650",
    "subDesc": "",
    "reward": "",
    "warning": 0,
    "dataBase": 0,
    "story": 0,
    "puzzle": ""
  },
  {
    "id": 50002003,
    "unlockCondition": "",
    "notFinish": 0,
    "desc": "language_10130651",
    "subDesc": "",
    "reward": "",
    "warning": 0,
    "dataBase": 0,
    "story": 0,
    "puzzle": ""
  },
  {
    "id": 50003001,
    "unlockCondition": "",
    "notFinish": 0,
    "desc": "language_10130652",
    "subDesc": "",
    "reward": "",
    "warning": 0,
    "dataBase": 0,
    "story": 0,
    "puzzle": ""
  },
  {
    "id": 50008001,
    "unlockCondition": "",
    "notFinish": 0,
    "desc": "language_10130653",
    "subDesc": "",
    "reward": "",
    "warning": 0,
    "dataBase": 0,
    "story": 0,
    "puzzle": ""
  },
  {
    "id": 50013001,
    "unlockCondition": "",
    "notFinish": 0,
    "desc": "language_10029298",
    "subDesc": "",
    "reward": "",
    "warning": 0,
    "dataBase": 0,
    "story": 0,
    "puzzle": ""
  },
  {
    "id": 50014001,
    "unlockCondition": "",
    "notFinish": 0,
    "desc": "language_10130654",
    "subDesc": "",
    "reward": "",
    "warning": -20,
    "dataBase": 0,
    "story": 0,
    "puzzle": ""
  },
  {
    "id": 50014002,
    "unlockCondition": "",
    "notFinish": 0,
    "desc": "language_10130655",
    "subDesc": "",
    "reward": "2#38501#13",
    "warning": 0,
    "dataBase": 0,
    "story": 0,
    "puzzle": ""
  },
  {
    "id": 50014003,
    "unlockCondition": "",
    "notFinish": 0,
    "desc": "language_10043097",
    "subDesc": "",
    "reward": "",
    "warning": 0,
    "dataBase": 0,
    "story": 0,
    "puzzle": ""
  },
  {
    "id": 50018001,
    "unlockCondition": "",
    "notFinish": 0,
    "desc": "language_10130656",
    "subDesc": "",
    "reward": "",
    "warning": 0,
    "dataBase": 0,
    "story": 0,
    "puzzle": ""
  },
  {
    "id": 50019001,
    "unlockCondition": "",
    "notFinish": 0,
    "desc": "language_10130657",
    "subDesc": "",
    "reward": "",
    "warning": 0,
    "dataBase": 0,
    "story": 0,
    "puzzle": ""
  },
  {
    "id": 50019002,
    "unlockCondition": "",
    "notFinish": 0,
    "desc": "language_10130658",
    "subDesc": "",
    "reward": "",
    "warning": 0,
    "dataBase": 0,
    "story": 0,
    "puzzle": ""
  },
  {
    "id": 101001001,
    "unlockCondition": "",
    "notFinish": 0,
    "desc": "language_90016067",
    "subDesc": "",
    "reward": "",
    "warning": 0,
    "dataBase": 0,
    "story": 0,
    "puzzle": ""
  },
  {
    "id": 101002001,
    "unlockCondition": "",
    "notFinish": 0,
    "desc": "language_90016067",
    "subDesc": "",
    "reward": "",
    "warning": 0,
    "dataBase": 0,
    "story": 0,
    "puzzle": ""
  },
  {
    "id": 101005001,
    "unlockCondition": "",
    "notFinish": 0,
    "desc": "language_90016067",
    "subDesc": "",
    "reward": "",
    "warning": 0,
    "dataBase": 0,
    "story": 0,
    "puzzle": ""
  },
  {
    "id": 101007001,
    "unlockCondition": "",
    "notFinish": 0,
    "desc": "language_90016067",
    "subDesc": "",
    "reward": "",
    "warning": 0,
    "dataBase": 0,
    "story": 0,
    "puzzle": ""
  },
  {
    "id": 101012001,
    "unlockCondition": "",
    "notFinish": 0,
    "desc": "language_90016067",
    "subDesc": "",
    "reward": "",
    "warning": 0,
    "dataBase": 0,
    "story": 0,
    "puzzle": ""
  },
  {
    "id": 101015001,
    "unlockCondition": "",
    "notFinish": 0,
    "desc": "language_10100425",
    "subDesc": "",
    "reward": "",
    "warning": 0,
    "dataBase": 0,
    "story": 0,
    "puzzle": ""
  },
  {
    "id": 102001001,
    "unlockCondition": "",
    "notFinish": 0,
    "desc": "language_90016067",
    "subDesc": "",
    "reward": "",
    "warning": 0,
    "dataBase": 0,
    "story": 0,
    "puzzle": ""
  },
  {
    "id": 102002001,
    "unlockCondition": "",
    "notFinish": 0,
    "desc": "language_90016067",
    "subDesc": "",
    "reward": "",
    "warning": 0,
    "dataBase": 0,
    "story": 0,
    "puzzle": ""
  },
  {
    "id": 102003001,
    "unlockCondition": "",
    "notFinish": 0,
    "desc": "language_90016067",
    "subDesc": "",
    "reward": "",
    "warning": 0,
    "dataBase": 0,
    "story": 0,
    "puzzle": ""
  },
  {
    "id": 102004001,
    "unlockCondition": "",
    "notFinish": 0,
    "desc": "language_90016067",
    "subDesc": "",
    "reward": "",
    "warning": 0,
    "dataBase": 0,
    "story": 0,
    "puzzle": ""
  },
  {
    "id": 102006001,
    "unlockCondition": "",
    "notFinish": 0,
    "desc": "language_90016067",
    "subDesc": "",
    "reward": "",
    "warning": 0,
    "dataBase": 0,
    "story": 0,
    "puzzle": ""
  },
  {
    "id": 102014001,
    "unlockCondition": "",
    "notFinish": 0,
    "desc": "language_10100425",
    "subDesc": "",
    "reward": "",
    "warning": 0,
    "dataBase": 0,
    "story": 0,
    "puzzle": ""
  },
  {
    "id": 103001001,
    "unlockCondition": "",
    "notFinish": 0,
    "desc": "language_90016067",
    "subDesc": "",
    "reward": "",
    "warning": 0,
    "dataBase": 0,
    "story": 0,
    "puzzle": ""
  },
  {
    "id": 103002001,
    "unlockCondition": "",
    "notFinish": 0,
    "desc": "language_90016067",
    "subDesc": "",
    "reward": "",
    "warning": 0,
    "dataBase": 0,
    "story": 0,
    "puzzle": ""
  },
  {
    "id": 103003001,
    "unlockCondition": "",
    "notFinish": 0,
    "desc": "language_90016067",
    "subDesc": "",
    "reward": "",
    "warning": 0,
    "dataBase": 0,
    "story": 0,
    "puzzle": ""
  },
  {
    "id": 103004001,
    "unlockCondition": "",
    "notFinish": 0,
    "desc": "language_90016067",
    "subDesc": "",
    "reward": "",
    "warning": 0,
    "dataBase": 0,
    "story": 0,
    "puzzle": ""
  },
  {
    "id": 103017001,
    "unlockCondition": "",
    "notFinish": 0,
    "desc": "language_10100425",
    "subDesc": "",
    "reward": "",
    "warning": 0,
    "dataBase": 0,
    "story": 0,
    "puzzle": ""
  },
  {
    "id": 104001001,
    "unlockCondition": "",
    "notFinish": 0,
    "desc": "language_90016067",
    "subDesc": "",
    "reward": "",
    "warning": 0,
    "dataBase": 0,
    "story": 0,
    "puzzle": ""
  },
  {
    "id": 104003001,
    "unlockCondition": "",
    "notFinish": 0,
    "desc": "language_90016067",
    "subDesc": "",
    "reward": "",
    "warning": 0,
    "dataBase": 0,
    "story": 0,
    "puzzle": ""
  },
  {
    "id": 104015001,
    "unlockCondition": "",
    "notFinish": 0,
    "desc": "language_10100425",
    "subDesc": "",
    "reward": "",
    "warning": 0,
    "dataBase": 0,
    "story": 0,
    "puzzle": ""
  },
  {
    "id": 105001001,
    "unlockCondition": "",
    "notFinish": 0,
    "desc": "language_90016067",
    "subDesc": "",
    "reward": "",
    "warning": 0,
    "dataBase": 0,
    "story": 0,
    "puzzle": ""
  },
  {
    "id": 105015001,
    "unlockCondition": "",
    "notFinish": 0,
    "desc": "language_10100425",
    "subDesc": "",
    "reward": "",
    "warning": 0,
    "dataBase": 0,
    "story": 0,
    "puzzle": ""
  }
]