[
  {
    "id": 1,
    "clueList": "101",
    "name": "language_10075942",
    "desc": "language_10075943",
    "type": "language_10079081",
    "notExposeName": "language_10079082",
    "tips": "language_10079083",
    "pos": 1,
    "isBoss": 0,
    "elementId": 130401,
    "icon": "640222",
    "autoExpose": 0
  },
  {
    "id": 2,
    "clueList": "201",
    "name": "language_10075944",
    "desc": "language_10075945",
    "type": "language_10079081",
    "notExposeName": "language_10079082",
    "tips": "language_10079083",
    "pos": 2,
    "isBoss": 0,
    "elementId": 130402,
    "icon": "640223",
    "autoExpose": 0
  },
  {
    "id": 3,
    "clueList": "301",
    "name": "language_10075946",
    "desc": "language_10075947",
    "type": "language_10079081",
    "notExposeName": "language_10079082",
    "tips": "language_10079084",
    "pos": 3,
    "isBoss": 0,
    "elementId": 130403,
    "icon": "630211",
    "autoExpose": 0
  },
  {
    "id": 4,
    "clueList": "401",
    "name": "language_10075948",
    "desc": "language_10075949",
    "type": "language_10079085",
    "notExposeName": "language_10079082",
    "tips": "language_10079086",
    "pos": 4,
    "isBoss": 0,
    "elementId": 230404,
    "icon": "670112",
    "autoExpose": 1
  },
  {
    "id": 5,
    "clueList": "501",
    "name": "language_10075950",
    "desc": "language_10075951",
    "type": "language_10079085",
    "notExposeName": "language_10079082",
    "tips": "language_10079086",
    "pos": 5,
    "isBoss": 0,
    "elementId": 230405,
    "icon": "620149",
    "autoExpose": 1
  },
  {
    "id": 6,
    "clueList": "601",
    "name": "language_10075952",
    "desc": "language_10075953",
    "type": "language_10079085",
    "notExposeName": "language_10079082",
    "tips": "language_10079087",
    "pos": 6,
    "isBoss": 0,
    "elementId": 330406,
    "icon": "630201",
    "autoExpose": 1
  },
  {
    "id": 7,
    "clueList": "701",
    "name": "language_10075954",
    "desc": "language_10075955",
    "type": "language_10079085",
    "notExposeName": "language_10079082",
    "tips": "language_10079087",
    "pos": 7,
    "isBoss": 0,
    "elementId": 330407,
    "icon": "670207",
    "autoExpose": 1
  },
  {
    "id": 8,
    "clueList": "801#802#803#804",
    "name": "language_10075956",
    "desc": "language_10075957",
    "type": "language_10079085",
    "notExposeName": "language_10079082",
    "tips": "language_10079088",
    "pos": 8,
    "isBoss": 0,
    "elementId": 330408,
    "icon": "620303",
    "autoExpose": 0
  },
  {
    "id": 9,
    "clueList": "901",
    "name": "language_10075958",
    "desc": "language_10075959",
    "type": "language_10079089",
    "notExposeName": "language_10079082",
    "tips": "language_10079090",
    "pos": 9,
    "isBoss": 0,
    "elementId": 430409,
    "icon": "670129",
    "autoExpose": 1
  },
  {
    "id": 10,
    "clueList": "1001",
    "name": "language_10075960",
    "desc": "language_10075961",
    "type": "language_10079089",
    "notExposeName": "language_10079082",
    "tips": "language_10079090",
    "pos": 10,
    "isBoss": 0,
    "elementId": 430410,
    "icon": "620136",
    "autoExpose": 1
  },
  {
    "id": 11,
    "clueList": "1101",
    "name": "language_10075962",
    "desc": "language_10075963",
    "type": "language_10079089",
    "notExposeName": "language_10079082",
    "tips": "language_10079091",
    "pos": 11,
    "isBoss": 0,
    "elementId": 530411,
    "icon": "620223",
    "autoExpose": 1
  },
  {
    "id": 12,
    "clueList": "1201#1202#1203",
    "name": "language_10075964",
    "desc": "language_10075965",
    "type": "language_10079089",
    "notExposeName": "language_10079082",
    "tips": "language_10079092",
    "pos": 12,
    "isBoss": 0,
    "elementId": 530412,
    "icon": "620312",
    "autoExpose": 0
  },
  {
    "id": 13,
    "clueList": "1301#1302#1303",
    "name": "language_10075966",
    "desc": "language_10079056",
    "type": "language_10079093",
    "notExposeName": "language_10079094",
    "tips": "language_10079095",
    "pos": 13,
    "isBoss": 1,
    "elementId": 430413,
    "icon": "670301",
    "autoExpose": 0
  }
]