[
  {
    "id": 1000,
    "name": "",
    "flag": "count0"
  },
  {
    "id": 1001,
    "name": "language_10081959",
    "flag": "count1"
  },
  {
    "id": 1002,
    "name": "language_10081960",
    "flag": "count2"
  },
  {
    "id": 1003,
    "name": "",
    "flag": "count3"
  },
  {
    "id": 1004,
    "name": "language_90001212",
    "flag": "count4"
  },
  {
    "id": 1005,
    "name": "",
    "flag": "count5"
  },
  {
    "id": 1006,
    "name": "",
    "flag": "count6"
  },
  {
    "id": 1007,
    "name": "",
    "flag": "count7"
  },
  {
    "id": 1008,
    "name": "",
    "flag": "count8"
  },
  {
    "id": 1009,
    "name": "",
    "flag": "count9"
  },
  {
    "id": 1010,
    "name": "",
    "flag": "count10"
  },
  {
    "id": 1011,
    "name": "",
    "flag": "count11"
  },
  {
    "id": 1012,
    "name": "",
    "flag": "count12"
  },
  {
    "id": 1013,
    "name": "",
    "flag": "count13"
  }
]